{
  "segments": {
    "right": [
      {
        "function": "powerline.segments.common.sys.uptime",
        "priority": 60,
        "args": {
          "shorten_len": 2
        }
      },
      {
        "function": "powerline.segments.common.sys.system_load",
        "priority": 50
      },
      {
        "function": "powerline.segments.common.bat.battery",
        "priority": 40
      },
      {
        "function": "powerline.segments.common.time.date",
        "name": "date",
        "args": {
          "format": "%m-%d"
        }
      },
      {
        "function": "powerline.segments.common.time.date",
        "name": "time",
        "args": {
          "format": "%H:%M",
          "istime": true
        }
      },
      {
        "function": "powerline.segments.common.env.user",
        "args": {
          "hide_domain": true
        },
        "draw_soft_divider": false
      },
      {
        "function": "powerline.segments.common.net.hostname",
        "draw_soft_divider": false
      }
    ]
  }
}
